CHANGELOG.md
LICENSE.txt
MANIFEST.in
README.md
requirements.txt
runtests.py
setup.py
django_node/__init__.py
django_node/base_service.py
django_node/exceptions.py
django_node/models.py
django_node/node.py
django_node/node_server.py
django_node/npm.py
django_node/package.json
django_node/package_dependent.py
django_node/server.py
django_node/settings.py
django_node/utils.py
django_node.egg-info/PKG-INFO
django_node.egg-info/SOURCES.txt
django_node.egg-info/dependency_links.txt
django_node.egg-info/requires.txt
django_node.egg-info/top_level.txt
django_node/management/__init__.py
django_node/management/commands/__init__.py
django_node/management/commands/install_package_dependencies.py
django_node/management/commands/node_server_config.py
django_node/management/commands/start_node_server.py
django_node/management/commands/uninstall_package_dependencies.py
django_node/services/__init__.py
django_node/services/echo.js