Metadata-Version: 1.0
Name: django-node
Version: 4.0.0
Summary: Bindings and utils for integrating Node.js and NPM into a Django application
Home-page: https://github.com/markfinger/django-node
Author: Mark Finger
Author-email: markfinger@gmail.com
License: UNKNOWN
Platform: UNKNOWN
